pyBCV/__init__.py
pyBCV/_requests.py
pyBCV/sistema_bancario.py
pyBCV/tasas_de_cambios.py
pyBCV/util.py
pyBCV-1.1.2.dist-info/LICENSE
pyBCV-1.1.2.dist-info/METADATA
pyBCV-1.1.2.dist-info/WHEEL
pyBCV-1.1.2.dist-info/top_level.txt
pyBCV-1.1.2.dist-info/RECORD
