Metadata-Version: 2.1
Name: pyBCV
Version: 1.1.2
Summary: PyBCV es una librería desarrollada en el lenguaje de programación Python que se utiliza para recopilar los precios de los tipos de cambio y las tasas informativas proporcionados por el Banco Central de Venezuela (BCV).
Home-page: https://github.com/fcoagz/pyBCV
Author: Francisco Griman
Author-email: Francisco Griman <grihardware@gmail.com>
License: MIT License
Project-URL: Homepage, https://github.com/fcoagz/pyBCV
Project-URL: Bug Tracker, https://github.com/fcoagz/pyBCV/issues
Keywords: bcv,analysis,precios,tasascambio,divisas,pybcv,venezuela
Classifier: Programming Language :: Python :: 3
Classifier: License :: OSI Approved :: MIT License
Classifier: Operating System :: OS Independent
Requires-Python: >=3.9
License-File: LICENSE
Requires-Dist: requests
Requires-Dist: bs4
Requires-Dist: beautifulsoup4
Requires-Dist: babel
